eth_portfolio/__init__.py
eth_portfolio/_argspec.py
eth_portfolio/_cache.py
eth_portfolio/_config.py
eth_portfolio/_decimal.py
eth_portfolio/_decorators.py
eth_portfolio/_exceptions.py
eth_portfolio/_shitcoins.py
eth_portfolio/_utils.py
eth_portfolio/address.py
eth_portfolio/buckets.py
eth_portfolio/constants.py
eth_portfolio/portfolio.py
eth_portfolio/py.typed
eth_portfolio/typing.py
eth_portfolio/_db/__init__.py
eth_portfolio/_db/decorators.py
eth_portfolio/_db/entities.py
eth_portfolio/_db/utils.py
eth_portfolio/_ledgers/__init__.py
eth_portfolio/_ledgers/address.py
eth_portfolio/_ledgers/portfolio.py
eth_portfolio/_loaders/__init__.py
eth_portfolio/_loaders/balances.py
eth_portfolio/_loaders/token_transfer.py
eth_portfolio/_loaders/transaction.py
eth_portfolio/_loaders/utils.py
eth_portfolio/_ydb/__init__.py
eth_portfolio/_ydb/token_transfers.py
eth_portfolio/protocols/__init__.py
eth_portfolio/protocols/_base.py
eth_portfolio/protocols/convex.py
eth_portfolio/protocols/dsr.py
eth_portfolio/protocols/liquity.py
eth_portfolio/protocols/lending/__init__.py
eth_portfolio/protocols/lending/_base.py
eth_portfolio/protocols/lending/compound.py
eth_portfolio/protocols/lending/liquity.py
eth_portfolio/protocols/lending/maker.py
eth_portfolio/protocols/lending/unit.py
eth_portfolio/structs/__init__.py
eth_portfolio/structs/modified.py
eth_portfolio/structs/structs.py
eth_portfolio-1.1.0.dist-info/METADATA
eth_portfolio-1.1.0.dist-info/WHEEL
eth_portfolio-1.1.0.dist-info/top_level.txt
eth_portfolio-1.1.0.dist-info/RECORD
