Metadata-Version: 2.2
Name: eth-portfolio
Version: 1.1.0
Summary: eth-portfolio makes it easy to analyze your portfolio.
Home-page: https://github.com/BobTheBuidler/eth-portfolio
Author: BobTheBuidler
Author-email: bobthebuidlerdefi@gmail.com
Project-URL: Homepage, https://github.com/BobTheBuidler/eth-portfolio
Project-URL: Documentation, https://bobthebuidler.github.io/eth-portfolio
Project-URL: Source Code, https://github.com/BobTheBuidler/eth-portfolio
Requires-Dist: checksum_dict>=1.1.2
Requires-Dist: dank_mids>=4.20.109
Requires-Dist: eth-brownie<1.21,>=1.19.3
Requires-Dist: eth_retry<1,>=0.1.15
Requires-Dist: evmspec>=0.2.0
Requires-Dist: ez-a-sync>=0.24.43
Requires-Dist: numpy<2
Requires-Dist: pandas<1.6,>=1.4.3
Requires-Dist: ypricemagic<5,>=4.0.57
Dynamic: author
Dynamic: author-email
Dynamic: description
Dynamic: description-content-type
Dynamic: home-page
Dynamic: project-url
Dynamic: requires-dist
Dynamic: summary
